django_powerpages-0.0.8.dist-info/DESCRIPTION.rst
django_powerpages-0.0.8.dist-info/METADATA
django_powerpages-0.0.8.dist-info/RECORD
django_powerpages-0.0.8.dist-info/WHEEL
django_powerpages-0.0.8.dist-info/metadata.json
django_powerpages-0.0.8.dist-info/top_level.txt
powerpages/__init__.py
powerpages/admin.py
powerpages/apps.py
powerpages/cachekeys.py
powerpages/dbfields.py
powerpages/formfields.py
powerpages/forms.py
powerpages/loader.py
powerpages/models.py
powerpages/page_processor_registry.py
powerpages/page_processors.py
powerpages/reverse.py
powerpages/settings.py
powerpages/signals.py
powerpages/sitemap.py
powerpages/sitemap_config.py
powerpages/sync.py
powerpages/urls.py
powerpages/views.py
powerpages/widgets.py
powerpages/management/__init__.py
powerpages/management/commands/__init__.py
powerpages/management/commands/website_base.py
powerpages/management/commands/website_dump.py
powerpages/management/commands/website_load.py
powerpages/migrations/0001_initial.py
powerpages/migrations/0002_auto_20170124_0055.py
powerpages/migrations/__init__.py
powerpages/static/powerpages/css/current_page_info.css
powerpages/static/powerpages/js/bind_ace_editor.js
powerpages/static/powerpages/js/ace/ace.js
powerpages/static/powerpages/js/ace/ext-chromevox.js
powerpages/static/powerpages/js/ace/ext-elastic_tabstops_lite.js
powerpages/static/powerpages/js/ace/ext-emmet.js
powerpages/static/powerpages/js/ace/ext-keybinding_menu.js
powerpages/static/powerpages/js/ace/ext-language_tools.js
powerpages/static/powerpages/js/ace/ext-modelist.js
powerpages/static/powerpages/js/ace/ext-old_ie.js
powerpages/static/powerpages/js/ace/ext-options.js
powerpages/static/powerpages/js/ace/ext-searchbox.js
powerpages/static/powerpages/js/ace/ext-settings_menu.js
powerpages/static/powerpages/js/ace/ext-spellcheck.js
powerpages/static/powerpages/js/ace/ext-split.js
powerpages/static/powerpages/js/ace/ext-static_highlight.js
powerpages/static/powerpages/js/ace/ext-statusbar.js
powerpages/static/powerpages/js/ace/ext-textarea.js
powerpages/static/powerpages/js/ace/ext-themelist.js
powerpages/static/powerpages/js/ace/ext-whitespace.js
powerpages/static/powerpages/js/ace/keybinding-emacs.js
