Metadata-Version: 2.0
Name: django-powerpages
Version: 0.0.8
Summary: Developer-friendly, simple CMS for Django, "flatpages on steroids".
Home-page: https://github.com/Open-E-WEB/django-powerpages
Author: Open-E, Inc.
Author-email: UNKNOWN
License: MIT
Keywords: django cms web
Platform: UNKNOWN
Classifier: Development Status :: 3 - Alpha
Classifier: Intended Audience :: Developers
Classifier: Environment :: Web Environment
Classifier: License :: OSI Approved :: MIT License
Classifier: Operating System :: OS Independent
Classifier: Programming Language :: Python :: 2
Classifier: Programming Language :: Python :: 2.7
Classifier: Programming Language :: Python :: 3
Classifier: Programming Language :: Python :: 3.4
Classifier: Programming Language :: Python :: 3.5
Classifier: Framework :: Django :: 1.9
Classifier: Framework :: Django :: 1.10
Classifier: Topic :: Internet :: WWW/HTTP
Requires-Dist: PyYAML (==3.11)
